metrohash.cp38-win_amd64.pyd
metrohash-0.4.1.dist-info/LICENSE
metrohash-0.4.1.dist-info/METADATA
metrohash-0.4.1.dist-info/WHEEL
metrohash-0.4.1.dist-info/top_level.txt
metrohash-0.4.1.dist-info/RECORD
