Metadata-Version: 2.1
Name: metrohash
Version: 0.4.1
Summary: Python bindings for MetroHash, a fast non-cryptographic hash algorithm
Home-page: https://github.com/escherba/python-metrohash
Author: Eugene Scherba
Author-email: escherba+metrohash@gmail.com
License: Apache License 2.0
Download-URL: https://github.com/escherba/python-metrohash/tarball/master/0.4.1
Keywords: hash,hashing,metrohash,cython
Platform: UNKNOWN
Classifier: Development Status :: 5 - Production/Stable
Classifier: Intended Audience :: Developers
Classifier: Intended Audience :: Science/Research
Classifier: License :: OSI Approved :: Apache Software License
Classifier: Operating System :: OS Independent
Classifier: Programming Language :: C++
Classifier: Programming Language :: Cython
Classifier: Programming Language :: Python :: 3.6
Classifier: Programming Language :: Python :: 3.7
Classifier: Programming Language :: Python :: 3.8
Classifier: Programming Language :: Python :: 3.9
Classifier: Programming Language :: Python :: 3.10
Classifier: Programming Language :: Python :: 3.11
Classifier: Programming Language :: Python :: 3.12
Classifier: Programming Language :: Python :: 3.13
Classifier: Topic :: Scientific/Engineering :: Information Analysis
Classifier: Topic :: Software Development :: Libraries
Classifier: Topic :: System :: Distributed Computing
Requires-Python: >=3.6
License-File: LICENSE
